dedenser/__init__.py
dedenser/__main__.py
dedenser/dedenser.py
dedenser/mcloud.py
dedenser-1.1.2.dist-info/LICENSE
dedenser-1.1.2.dist-info/LICENSES_THIRD_PARTY
dedenser-1.1.2.dist-info/METADATA
dedenser-1.1.2.dist-info/WHEEL
dedenser-1.1.2.dist-info/entry_points.txt
dedenser-1.1.2.dist-info/top_level.txt
dedenser-1.1.2.dist-info/RECORD
