Metadata-Version: 2.1
Name: dedenser
Version: 1.1.2
Summary: An application for downsampling chemical point clouds.
Home-page: https://github.com/MSDLLCpapers/dedenser
Author: Armen G. Beck
Author-email: armen.beck@merck.com
License: UNKNOWN
Platform: UNKNOWN
Classifier: Development Status :: 4 - Beta
Classifier: Environment :: Console
Classifier: Intended Audience :: Science/Research
Classifier: License :: OSI Approved :: BSD License
Classifier: Operating System :: Microsoft :: Windows
Classifier: Operating System :: Unix
Classifier: Programming Language :: Python :: 3
Classifier: Topic :: Scientific/Engineering :: Chemistry
Requires-Python: >=3.8.2
License-File: LICENSE
License-File: LICENSES_THIRD_PARTY
Requires-Dist: numpy (>=1.24.4)
Requires-Dist: pandas
Requires-Dist: openpyxl
Requires-Dist: mordred (>=1.2.0)
Requires-Dist: rdkit
Requires-Dist: scikit-learn (>=1.3.0)
Requires-Dist: alphashape (>=1.3.1)
Requires-Dist: scipy (>=1.10.1)
Requires-Dist: point-cloud-utils (==0.30.4)
Requires-Dist: umap-learn (>=0.5.5)
Requires-Dist: matplotlib
Requires-Dist: future
Requires-Dist: plotly
Requires-Dist: dash
